{
    "channel_name": "Голос Шансона",
    "channel_id": "UCYDG8kZww12RpW-ZgleE2Iw",
    "filter_used": "VIDEO",
    "created_at": "2025-06-30T11:14:30.583934Z",
    "total_views": 6235612,
    "subscribers": 31200,
    "style": "Жизненный Шансон / Бардовская Исповедь",
    "emojis": "🎸🔥",
    "emoji": "♠️",
    "description": "🎙 ГОЛОС ШАНСОНА — это не просто канал. Это музыка, в которой живут чувства.\nЗдесь звучит душевный шансон — для тех, кто знает цену жизни, помнит настоящую дружбу, пережил любовь, потери, дорогу, предательство… и остался с сердцем.\nКаждая песня на канале — это история. Про мужчин с характером и женщин с огнём в глазах. Про улицы, где всё решается без лишних слов. Про надежду, которая остаётся даже в самую тёмную ночь.\n\n🔊 На канале вы найдёте:\nАвторские песни в стиле классического шансона\nТреки о жизни, свободе, любви, разлуке, зоне и вере\nМузыку под настроение: и чтобы подумать, и чтобы выпить молча\nДушевный голос, живой текст, настоящие эмоции\n\n🎼 Хочешь услышать свою историю в песне?\nМы делаем песни на заказ — с нуля, под твою ситуацию или эмоции. Расскажешь — напишем. И никто, кроме тебя, не будет иметь такую композицию.\n📬 По вопросам индивидуального заказа обращайся на почту:\ngolos.shansona@gmail.com\n\nПодпишись, слушай, чувствуй.\nГОЛОС ШАНСОНА — от души и для души.\n",
    "thumbnails": {
        "default": {
            "url": "https://yt3.ggpht.com/Qcfh404y5s7ERy0fI6z1s_-3iWDG-_zkiabOQmbvXYjpBanTUTYGQey9JZb_Q9HLXPfNu1BXSg=s88-c-k-c0x00ffffff-no-rj",
            "width": 88,
            "height": 88
        },
        "medium": {
            "url": "https://yt3.ggpht.com/Qcfh404y5s7ERy0fI6z1s_-3iWDG-_zkiabOQmbvXYjpBanTUTYGQey9JZb_Q9HLXPfNu1BXSg=s240-c-k-c0x00ffffff-no-rj",
            "width": 240,
            "height": 240
        },
        "high": {
            "url": "https://yt3.ggpht.com/Qcfh404y5s7ERy0fI6z1s_-3iWDG-_zkiabOQmbvXYjpBanTUTYGQey9JZb_Q9HLXPfNu1BXSg=s800-c-k-c0x00ffffff-no-rj",
            "width": 800,
            "height": 800
        }
    },
    "videos": [
        {
            "video_id": "DBjx0UztS20",
            "title": "Она пела… Я влюбился | НОВОГОДНИЙ ШАНСОН",
            "type": "video",
            "published_at": "2025-12-27T15:00:32Z",
            "duration": "0:04:50",
            "duration_sec": 290,
            "views": 245,
            "likes": 18,
            "comments": 4,
            "url": "https://www.youtube.com/watch?v=DBjx0UztS20"
        },
        {
            "video_id": "yHBGacRXIHk",
            "title": "С лёгким паром, родные | НОВОГОДНИЙ ШАНСОН",
            "type": "video",
            "published_at": "2025-12-26T15:02:01Z",
            "duration": "0:03:59",
            "duration_sec": 239,
            "views": 628,
            "likes": 37,
            "comments": 5,
            "url": "https://www.youtube.com/watch?v=yHBGacRXIHk"
        },
        {
            "video_id": "kN1lQVZLkl0",
            "title": "НОВОГОДНИЙ ШАНСОН — Тост за счастье",
            "type": "video",
            "published_at": "2025-12-25T15:01:32Z",
            "duration": "0:05:55",
            "duration_sec": 355,
            "views": 2689,
            "likes": 105,
            "comments": 14,
            "url": "https://www.youtube.com/watch?v=kN1lQVZLkl0"
        },
        {
            "video_id": "DHOwg3O6NYQ",
            "title": "Лучшие Новогодние Песни — Сборник для Всей Семьи",
            "type": "video",
            "published_at": "2025-12-22T07:00:08Z",
            "duration": "1:16:12",
            "duration_sec": 4572,
            "views": 75172,
            "likes": 211,
            "comments": 17,
            "url": "https://www.youtube.com/watch?v=DHOwg3O6NYQ"
        },
        {
            "video_id": "6Nnuttwyr7I",
            "title": "ШАНСОН. Этот год был тяжёлым… но я его отпускаю",
            "type": "video",
            "published_at": "2025-12-20T15:00:11Z",
            "duration": "0:05:19",
            "duration_sec": 319,
            "views": 4357,
            "likes": 193,
            "comments": 22,
            "url": "https://www.youtube.com/watch?v=6Nnuttwyr7I"
        },
        {
            "video_id": "dU3YYD-Sl1Q",
            "title": "НОВОГОДНИЙ ШАНСОН — Свет В Конце Тоннеля",
            "type": "video",
            "published_at": "2025-12-19T15:01:25Z",
            "duration": "0:04:55",
            "duration_sec": 295,
            "views": 2015,
            "likes": 76,
            "comments": 7,
            "url": "https://www.youtube.com/watch?v=dU3YYD-Sl1Q"
        },
        {
            "video_id": "ZsKbJnWnPI4",
            "title": "Я Проснулся — И это уже счастье | ЖИЗНЕННЫЙ ШАНСОН",
            "type": "video",
            "published_at": "2025-12-18T15:00:59Z",
            "duration": "0:05:41",
            "duration_sec": 341,
            "views": 1514,
            "likes": 64,
            "comments": 11,
            "url": "https://www.youtube.com/watch?v=ZsKbJnWnPI4"
        },
        {
            "video_id": "N3_YyQ9VwUU",
            "title": "Новогодний Танцевальный СБОРНИК — Хиты для Праздника",
            "type": "video",
            "published_at": "2025-12-16T07:15:04Z",
            "duration": "1:01:46",
            "duration_sec": 3706,
            "views": 12731,
            "likes": 181,
            "comments": 13,
            "url": "https://www.youtube.com/watch?v=N3_YyQ9VwUU"
        },
        {
            "video_id": "aJ08E-hHDpI",
            "title": "Не Уходит Молодость — ШАНСОН, Что Тронет Душу",
            "type": "video",
            "published_at": "2025-12-13T15:15:00Z",
            "duration": "0:03:39",
            "duration_sec": 219,
            "views": 5282,
            "likes": 175,
            "comments": 11,
            "url": "https://www.youtube.com/watch?v=aJ08E-hHDpI"
        },
        {
            "video_id": "8SX6AN0gu8s",
            "title": "Песня для тех, кто один… Настоящий душевный ШАНСОН",
            "type": "video",
            "published_at": "2025-12-12T15:00:16Z",
            "duration": "0:04:58",
            "duration_sec": 298,
            "views": 3218,
            "likes": 128,
            "comments": 18,
            "url": "https://www.youtube.com/watch?v=8SX6AN0gu8s"
        },
        {
            "video_id": "-1C_Tt7DbCw",
            "title": "Застольные Новогодние Песни — Весёлый Сборник Хитов",
            "type": "video",
            "published_at": "2025-12-10T07:15:01Z",
            "duration": "1:03:49",
            "duration_sec": 3829,
            "views": 11140,
            "likes": 204,
            "comments": 12,
            "url": "https://www.youtube.com/watch?v=-1C_Tt7DbCw"
        },
        {
            "video_id": "sUes7MFt8DM",
            "title": "Ночной город — ШАНСОН, который бьёт в самое сердце",
            "type": "video",
            "published_at": "2025-12-09T15:01:56Z",
            "duration": "0:05:31",
            "duration_sec": 331,
            "views": 1233,
            "likes": 45,
            "comments": 11,
            "url": "https://www.youtube.com/watch?v=sUes7MFt8DM"
        },
        {
            "video_id": "1WpIXekmgBQ",
            "title": "Моя Звезда — Новый Душевный ШАНСОН о Судьбе и Жизни",
            "type": "video",
            "published_at": "2025-12-08T15:00:02Z",
            "duration": "0:03:57",
            "duration_sec": 237,
            "views": 1480,
            "likes": 74,
            "comments": 9,
            "url": "https://www.youtube.com/watch?v=1WpIXekmgBQ"
        },
        {
            "video_id": "Ls6SkpYs1Aw",
            "title": "САМОГОННЫЙ ШАНСОН — Новогодний Хит для Души",
            "type": "video",
            "published_at": "2025-12-07T15:00:47Z",
            "duration": "0:04:30",
            "duration_sec": 270,
            "views": 1530,
            "likes": 66,
            "comments": 15,
            "url": "https://www.youtube.com/watch?v=Ls6SkpYs1Aw"
        },
        {
            "video_id": "qaI_kkaQ-Ws",
            "title": "Новогодний ШАНСОН — Сборник Душевных Праздничных Хитов",
            "type": "video",
            "published_at": "2025-12-05T07:01:00Z",
            "duration": "2:00:03",
            "duration_sec": 7203,
            "views": 47082,
            "likes": 786,
            "comments": 52,
            "url": "https://www.youtube.com/watch?v=qaI_kkaQ-Ws"
        },
        {
            "video_id": "NKRxaTV_YBs",
            "title": "ПЕРВОЕ ДЕКАБРЯ — Русский ШАНСОН о Времени и Судьбе",
            "type": "video",
            "published_at": "2025-12-01T16:00:43Z",
            "duration": "0:04:17",
            "duration_sec": 257,
            "views": 2203,
            "likes": 84,
            "comments": 15,
            "url": "https://www.youtube.com/watch?v=NKRxaTV_YBs"
        },
        {
            "video_id": "gVrz3srJe0M",
            "title": "ВОПРОС БОГУ — Новый Душевный ШАНСОН О ЖИЗНИ",
            "type": "video",
            "published_at": "2025-11-30T11:01:19Z",
            "duration": "0:05:39",
            "duration_sec": 339,
            "views": 5312,
            "likes": 211,
            "comments": 35,
            "url": "https://www.youtube.com/watch?v=gVrz3srJe0M"
        },
        {
            "video_id": "d2wYo4EAwtM",
            "title": "Когда осень в душе… Помни о весне | Душевный ШАНСОН",
            "type": "video",
            "published_at": "2025-11-29T11:01:12Z",
            "duration": "0:05:28",
            "duration_sec": 328,
            "views": 4103,
            "likes": 123,
            "comments": 15,
            "url": "https://www.youtube.com/watch?v=d2wYo4EAwtM"
        },
        {
            "video_id": "H-aG_rk3dUs",
            "title": "ЧТО ОСТАНЕТСЯ ПОСЛЕ НАС? МОЩНЫЙ РУССКИЙ ШАНСОН",
            "type": "video",
            "published_at": "2025-11-28T17:00:24Z",
            "duration": "0:04:58",
            "duration_sec": 298,
            "views": 49079,
            "likes": 1508,
            "comments": 89,
            "url": "https://www.youtube.com/watch?v=H-aG_rk3dUs"
        },
        {
            "video_id": "9igrY0aPNhc",
            "title": "Годы В Стрелках Часов — Новый Жизненный ШАНСОН",
            "type": "video",
            "published_at": "2025-11-27T17:00:17Z",
            "duration": "0:04:23",
            "duration_sec": 263,
            "views": 2096,
            "likes": 68,
            "comments": 17,
            "url": "https://www.youtube.com/watch?v=9igrY0aPNhc"
        },
        {
            "video_id": "Vht8W4Ro0xA",
            "title": "С ДНЁМ РОЖДЕНИЯ! Новый хит русского шансона",
            "type": "video",
            "published_at": "2025-11-26T17:00:56Z",
            "duration": "0:05:08",
            "duration_sec": 308,
            "views": 5554,
            "likes": 128,
            "comments": 6,
            "url": "https://www.youtube.com/watch?v=Vht8W4Ro0xA"
        },
        {
            "video_id": "FJuEeNBroFk",
            "title": "ЖИЗНЕННЫЙ ШАНСОН о пути, где нет дороги назад",
            "type": "video",
            "published_at": "2025-11-25T17:00:24Z",
            "duration": "0:03:26",
            "duration_sec": 206,
            "views": 1525,
            "likes": 28,
            "comments": 5,
            "url": "https://www.youtube.com/watch?v=FJuEeNBroFk"
        },
        {
            "video_id": "kOMezfzCwBA",
            "title": "Честный ШАНСОН для души — Ошибки, что спасли мне жизнь",
            "type": "video",
            "published_at": "2025-11-24T17:01:32Z",
            "duration": "0:05:41",
            "duration_sec": 341,
            "views": 2675,
            "likes": 92,
            "comments": 15,
            "url": "https://www.youtube.com/watch?v=kOMezfzCwBA"
        },
        {
            "video_id": "RrLk0QmwEqU",
            "title": "Несказанные Слова — ШАНСОН, который попадает ПРЯМО В СЕРДЦЕ",
            "type": "video",
            "published_at": "2025-11-23T11:00:53Z",
            "duration": "0:06:37",
            "duration_sec": 397,
            "views": 4891,
            "likes": 169,
            "comments": 36,
            "url": "https://www.youtube.com/watch?v=RrLk0QmwEqU"
        },
        {
            "video_id": "t1qD3IBUf_c",
            "title": "ШАНСОН ПРО ЗАВИСИМОСТЬ, КОТОРЫЙ ВЫТАСКИВАЕТ С ДНА",
            "type": "video",
            "published_at": "2025-11-22T11:01:53Z",
            "duration": "0:04:13",
            "duration_sec": 253,
            "views": 2953,
            "likes": 102,
            "comments": 10,
            "url": "https://www.youtube.com/watch?v=t1qD3IBUf_c"
        },
        {
            "video_id": "zyrevOGgbnA",
            "title": "Жизнь как Гора — Новый Жизненный ШАНСОН",
            "type": "video",
            "published_at": "2025-11-21T17:01:58Z",
            "duration": "0:05:20",
            "duration_sec": 320,
            "views": 2171,
            "likes": 83,
            "comments": 15,
            "url": "https://www.youtube.com/watch?v=zyrevOGgbnA"
        },
        {
            "video_id": "npa57K81MuU",
            "title": "ШАНСОН: ОНА ОХОТИТСЯ В НОЧИ… ТЫ МОЖЕШЬ ПОПАСТЬ В ЛОВУШКУ",
            "type": "video",
            "published_at": "2025-11-20T17:01:25Z",
            "duration": "0:03:17",
            "duration_sec": 197,
            "views": 718,
            "likes": 27,
            "comments": 3,
            "url": "https://www.youtube.com/watch?v=npa57K81MuU"
        },
        {
            "video_id": "oEVh-poXEa4",
            "title": "Все плохое ушло — самый душевный ШАНСОН года",
            "type": "video",
            "published_at": "2025-11-19T17:01:32Z",
            "duration": "0:04:48",
            "duration_sec": 288,
            "views": 3667,
            "likes": 106,
            "comments": 9,
            "url": "https://www.youtube.com/watch?v=oEVh-poXEa4"
        },
        {
            "video_id": "CdfTKiSUHWk",
            "title": "ШАНСОН о родителях, который ТРОГАЕТ ДО СЛЁЗ",
            "type": "video",
            "published_at": "2025-11-18T17:00:15Z",
            "duration": "0:05:38",
            "duration_sec": 338,
            "views": 72374,
            "likes": 1838,
            "comments": 86,
            "url": "https://www.youtube.com/watch?v=CdfTKiSUHWk"
        },
        {
            "video_id": "UG53Vh9CXj4",
            "title": "ЖИЗНЬ — КАК РЕКА: Новый ШАНСОН, что тронет сердце",
            "type": "video",
            "published_at": "2025-11-17T17:00:50Z",
            "duration": "0:04:38",
            "duration_sec": 278,
            "views": 3485,
            "likes": 141,
            "comments": 14,
            "url": "https://www.youtube.com/watch?v=UG53Vh9CXj4"
        },
        {
            "video_id": "XKSM6cmVLU8",
            "title": "Душевная песня на День Рождения — лучшее поздравление",
            "type": "video",
            "published_at": "2025-11-16T11:01:05Z",
            "duration": "0:04:38",
            "duration_sec": 278,
            "views": 99038,
            "likes": 3184,
            "comments": 114,
            "url": "https://www.youtube.com/watch?v=XKSM6cmVLU8"
        },
        {
            "video_id": "bglqKJi2-M4",
            "title": "Не будь в стаде — мощный авторский ШАНСОН о свободе",
            "type": "video",
            "published_at": "2025-11-15T11:01:14Z",
            "duration": "0:04:30",
            "duration_sec": 270,
            "views": 5349,
            "likes": 214,
            "comments": 15,
            "url": "https://www.youtube.com/watch?v=bglqKJi2-M4"
        },
        {
            "video_id": "Sllnjg_LaWg",
            "title": "СЛЁЗЫ НЕ СТЫД — Шансон, который тронет каждого",
            "type": "video",
            "published_at": "2025-11-14T17:00:53Z",
            "duration": "0:05:04",
            "duration_sec": 304,
            "views": 14533,
            "likes": 400,
            "comments": 50,
            "url": "https://www.youtube.com/watch?v=Sllnjg_LaWg"
        },
        {
            "video_id": "Zk-J7lVxFlg",
            "title": "ВОЗРАСТ — ЭТО ПЫЛЬ | Душевный ШАНСОН о жизни и душе",
            "type": "video",
            "published_at": "2025-11-13T17:01:04Z",
            "duration": "0:05:18",
            "duration_sec": 318,
            "views": 32758,
            "likes": 751,
            "comments": 57,
            "url": "https://www.youtube.com/watch?v=Zk-J7lVxFlg"
        },
        {
            "video_id": "IqfexMpAPj4",
            "title": "Когда голос пьян, но душа поёт — Настоящий ШАНСОН",
            "type": "video",
            "published_at": "2025-11-12T17:00:36Z",
            "duration": "0:03:39",
            "duration_sec": 219,
            "views": 1312,
            "likes": 40,
            "comments": 4,
            "url": "https://www.youtube.com/watch?v=IqfexMpAPj4"
        },
        {
            "video_id": "RwXBTzhKEfw",
            "title": "Он спел это из тюрьмы — и плакали все | РУССКИЙ ШАНСОН",
            "type": "video",
            "published_at": "2025-11-11T17:00:45Z",
            "duration": "0:04:38",
            "duration_sec": 278,
            "views": 4596,
            "likes": 121,
            "comments": 14,
            "url": "https://www.youtube.com/watch?v=RwXBTzhKEfw"
        },
        {
            "video_id": "y29biXIFcmU",
            "title": "Слушай, пока жив — НАСТОЯЩИЙ ШАНСОН О СМЫСЛЕ ЖИЗНИ",
            "type": "video",
            "published_at": "2025-11-10T17:01:45Z",
            "duration": "0:04:16",
            "duration_sec": 256,
            "views": 3002,
            "likes": 112,
            "comments": 13,
            "url": "https://www.youtube.com/watch?v=y29biXIFcmU"
        },
        {
            "video_id": "BPTTVdk4bTU",
            "title": "ПЕСНЯ, ПОД КОТОРУЮ ЗАБЫВАЮТ ВСЕ ПРОБЛЕМЫ",
            "type": "video",
            "published_at": "2025-11-09T11:00:30Z",
            "duration": "0:03:21",
            "duration_sec": 201,
            "views": 4197,
            "likes": 107,
            "comments": 11,
            "url": "https://www.youtube.com/watch?v=BPTTVdk4bTU"
        },
        {
            "video_id": "o0btzXckjN4",
            "title": "ОН ПОНЯЛ ВСЁ… НО ТОЛЬКО ПОД КОНЕЦ | Русский ШАНСОН",
            "type": "video",
            "published_at": "2025-11-08T11:01:34Z",
            "duration": "0:04:46",
            "duration_sec": 286,
            "views": 6709,
            "likes": 227,
            "comments": 22,
            "url": "https://www.youtube.com/watch?v=o0btzXckjN4"
        },
        {
            "video_id": "7rk3RirWx-E",
            "title": "НЕ СУДИ, БРАТ… ШАНСОН, который поменяет твоё сердце",
            "type": "video",
            "published_at": "2025-11-07T17:00:26Z",
            "duration": "0:03:25",
            "duration_sec": 205,
            "views": 9363,
            "likes": 240,
            "comments": 10,
            "url": "https://www.youtube.com/watch?v=7rk3RirWx-E"
        },
        {
            "video_id": "97qkbqKEwyE",
            "title": "ШАНСОН о пути, жизни и благодарности — «Благодарю»",
            "type": "video",
            "published_at": "2025-11-06T17:00:23Z",
            "duration": "0:04:18",
            "duration_sec": 258,
            "views": 10146,
            "likes": 302,
            "comments": 25,
            "url": "https://www.youtube.com/watch?v=97qkbqKEwyE"
        },
        {
            "video_id": "jpJRPuGRyz0",
            "title": "ШАНСОН для ТВОЕГО ДНЯ РОЖДЕНИЯ — Пей за счастье!",
            "type": "video",
            "published_at": "2025-11-05T17:01:22Z",
            "duration": "0:04:04",
            "duration_sec": 244,
            "views": 10233,
            "likes": 288,
            "comments": 12,
            "url": "https://www.youtube.com/watch?v=jpJRPuGRyz0"
        },
        {
            "video_id": "1v48171iNrM",
            "title": "ПОЗДНИЙ ПОЕЗД — ШАНСОН, от которого молчат сердца",
            "type": "video",
            "published_at": "2025-11-04T17:00:08Z",
            "duration": "0:04:02",
            "duration_sec": 242,
            "views": 106514,
            "likes": 1915,
            "comments": 57,
            "url": "https://www.youtube.com/watch?v=1v48171iNrM"
        },
        {
            "video_id": "pT-GAV2tJxo",
            "title": "Любовь пришла, когда уже не ждал… | ШАНСОН, от которого мурашки",
            "type": "video",
            "published_at": "2025-11-03T17:01:25Z",
            "duration": "0:04:16",
            "duration_sec": 256,
            "views": 2896,
            "likes": 132,
            "comments": 5,
            "url": "https://www.youtube.com/watch?v=pT-GAV2tJxo"
        },
        {
            "video_id": "GZ1xCZsYcj0",
            "title": "БЕРИ ВСЁ ОТ ЖИЗНИ — ЗАСТОЛЬНАЯ ПЕСНЯ, которая тронет душу",
            "type": "video",
            "published_at": "2025-11-02T11:00:27Z",
            "duration": "0:03:29",
            "duration_sec": 209,
            "views": 2465,
            "likes": 81,
            "comments": 8,
            "url": "https://www.youtube.com/watch?v=GZ1xCZsYcj0"
        },
        {
            "video_id": "A2p9iDK2XcQ",
            "title": "Последняя ночь перед зоной | ШАНСОН до мурашек",
            "type": "video",
            "published_at": "2025-11-01T11:00:31Z",
            "duration": "0:03:17",
            "duration_sec": 197,
            "views": 1959,
            "likes": 42,
            "comments": 3,
            "url": "https://www.youtube.com/watch?v=A2p9iDK2XcQ"
        },
        {
            "video_id": "HRw-9vZ3Gyk",
            "title": "ШАНСОН до слёз — Он едет к ней сквозь ночь и дождь",
            "type": "video",
            "published_at": "2025-10-31T17:00:35Z",
            "duration": "0:03:58",
            "duration_sec": 238,
            "views": 5103,
            "likes": 138,
            "comments": 7,
            "url": "https://www.youtube.com/watch?v=HRw-9vZ3Gyk"
        },
        {
            "video_id": "-3Ua4dh7-vQ",
            "title": "СВЯТОЙ ДОЖДЬ — ШАНСОН, который пробирает до костей",
            "type": "video",
            "published_at": "2025-10-30T17:00:00Z",
            "duration": "0:05:14",
            "duration_sec": 314,
            "views": 26141,
            "likes": 717,
            "comments": 42,
            "url": "https://www.youtube.com/watch?v=-3Ua4dh7-vQ"
        },
        {
            "video_id": "25GojEkQ8PM",
            "title": "Все зовут её КАРНАВАЛ... ШАНСОН о любви и судьбе",
            "type": "video",
            "published_at": "2025-10-29T17:00:05Z",
            "duration": "0:03:30",
            "duration_sec": 210,
            "views": 1624,
            "likes": 50,
            "comments": 4,
            "url": "https://www.youtube.com/watch?v=25GojEkQ8PM"
        },
        {
            "video_id": "TbFV97wALo8",
            "title": "Падал, но вставал — ШАНСОН, что тронет сердце",
            "type": "video",
            "published_at": "2025-10-28T17:00:49Z",
            "duration": "0:03:55",
            "duration_sec": 235,
            "views": 14382,
            "likes": 393,
            "comments": 14,
            "url": "https://www.youtube.com/watch?v=TbFV97wALo8"
        },
        {
            "video_id": "yiYsnAzoVbE",
            "title": "Жизнь — как дорога в тумане | ШАНСОН, КОТОРЫЙ ТРОГАЕТ ДУШУ",
            "type": "video",
            "published_at": "2025-10-27T17:01:36Z",
            "duration": "0:04:45",
            "duration_sec": 285,
            "views": 33049,
            "likes": 663,
            "comments": 28,
            "url": "https://www.youtube.com/watch?v=yiYsnAzoVbE"
        },
        {
            "video_id": "zPMe_fj8Vxo",
            "title": "Прожил немало… но жизнь только начинается | ШАНСОН",
            "type": "video",
            "published_at": "2025-10-26T11:01:47Z",
            "duration": "0:04:23",
            "duration_sec": 263,
            "views": 167957,
            "likes": 2170,
            "comments": 98,
            "url": "https://www.youtube.com/watch?v=zPMe_fj8Vxo"
        },
        {
            "video_id": "U-k25-Th4ck",
            "title": "ПО РЕЛЬСАМ СУДЬБЫ | Душевный ШАНСОН о судьбе и людях",
            "type": "video",
            "published_at": "2025-10-25T10:00:47Z",
            "duration": "0:03:27",
            "duration_sec": 207,
            "views": 7036,
            "likes": 135,
            "comments": 16,
            "url": "https://www.youtube.com/watch?v=U-k25-Th4ck"
        },
        {
            "video_id": "fEvgZMnyiUI",
            "title": "ЗА ЧЕЛОВЕКА ДНЯ! 🎂 ШАНСОН НА ДЕНЬ РОЖДЕНИЯ",
            "type": "video",
            "published_at": "2025-10-24T16:01:23Z",
            "duration": "0:04:09",
            "duration_sec": 249,
            "views": 3384,
            "likes": 98,
            "comments": 4,
            "url": "https://www.youtube.com/watch?v=fEvgZMnyiUI"
        },
        {
            "video_id": "4jGzjpV2ptQ",
            "title": "Она нашла письма… и изменила судьбу | душевный ШАНСОН",
            "type": "video",
            "published_at": "2025-10-23T16:00:11Z",
            "duration": "0:04:42",
            "duration_sec": 282,
            "views": 809,
            "likes": 30,
            "comments": 6,
            "url": "https://www.youtube.com/watch?v=4jGzjpV2ptQ"
        },
        {
            "video_id": "3umxw-RaZHI",
            "title": "ОН ОСТАЛСЯ ОДИН — Русский ШАНСОН, который тронет сердце",
            "type": "video",
            "published_at": "2025-10-22T16:00:07Z",
            "duration": "0:04:35",
            "duration_sec": 275,
            "views": 134417,
            "likes": 2616,
            "comments": 116,
            "url": "https://www.youtube.com/watch?v=3umxw-RaZHI"
        },
        {
            "video_id": "-OLZqvtVGYU",
            "title": "Из ГРЯЗИ — в ПАРИЖ! Честный РУССКИЙ ШАНСОН",
            "type": "video",
            "published_at": "2025-10-21T16:00:00Z",
            "duration": "0:03:19",
            "duration_sec": 199,
            "views": 1987,
            "likes": 58,
            "comments": 21,
            "url": "https://www.youtube.com/watch?v=-OLZqvtVGYU"
        },
        {
            "video_id": "EUZUvwmJVKY",
            "title": "ПОКА ЖИВЫ РОДИТЕЛИ — СПЕШИ ДОМОЙ... ШАНСОН ДО СЛЁЗ",
            "type": "video",
            "published_at": "2025-10-20T16:00:19Z",
            "duration": "0:04:32",
            "duration_sec": 272,
            "views": 15826,
            "likes": 493,
            "comments": 13,
            "url": "https://www.youtube.com/watch?v=EUZUvwmJVKY"
        },
        {
            "video_id": "-cox9ksvXiw",
            "title": "НЕ ЗАВИДУЙ НИКОМУ - настоящий ШАНСОН от души!",
            "type": "video",
            "published_at": "2025-10-19T10:00:00Z",
            "duration": "0:03:53",
            "duration_sec": 233,
            "views": 7256,
            "likes": 210,
            "comments": 12,
            "url": "https://www.youtube.com/watch?v=-cox9ksvXiw"
        },
        {
            "video_id": "96bts4U4x1s",
            "title": "Девичник по-русски! Смех, слёзы и ЗАСТОЛЬНЫЙ ШАНСОН",
            "type": "video",
            "published_at": "2025-10-18T10:15:01Z",
            "duration": "0:04:37",
            "duration_sec": 277,
            "views": 4120,
            "likes": 97,
            "comments": 5,
            "url": "https://www.youtube.com/watch?v=96bts4U4x1s"
        },
        {
            "video_id": "Z3HpKuLjjT0",
            "title": "НАСТЯ, АНАСТАСИЯ — ПЕСНЯ, КОТОРАЯ ЗАЦЕПИТ СЕРДЦЕ 💔",
            "type": "video",
            "published_at": "2025-10-17T16:01:00Z",
            "duration": "0:04:26",
            "duration_sec": 266,
            "views": 3055,
            "likes": 69,
            "comments": 4,
            "url": "https://www.youtube.com/watch?v=Z3HpKuLjjT0"
        },
        {
            "video_id": "-hTY92icD3E",
            "title": "Последние слова перед вечностью | ШАНСОН до мурашек",
            "type": "video",
            "published_at": "2025-10-16T16:00:00Z",
            "duration": "0:03:50",
            "duration_sec": 230,
            "views": 2930,
            "likes": 94,
            "comments": 12,
            "url": "https://www.youtube.com/watch?v=-hTY92icD3E"
        },
        {
            "video_id": "DFH2xijqIJ4",
            "title": "БЕЗ НИЧЕГО — ШАНСОН, КОТОРЫЙ ЗАСТАВИТ ЗАДУМАТЬСЯ",
            "type": "video",
            "published_at": "2025-10-15T16:00:26Z",
            "duration": "0:05:03",
            "duration_sec": 303,
            "views": 142081,
            "likes": 2701,
            "comments": 173,
            "url": "https://www.youtube.com/watch?v=DFH2xijqIJ4"
        },
        {
            "video_id": "MOBa3lq7CJI",
            "title": "Питер во мне | Душевная песня о родном городе (русский шансон)",
            "type": "video",
            "published_at": "2025-10-14T16:00:48Z",
            "duration": "0:04:59",
            "duration_sec": 299,
            "views": 1681,
            "likes": 38,
            "comments": 6,
            "url": "https://www.youtube.com/watch?v=MOBa3lq7CJI"
        },
        {
            "video_id": "rTa7kvPdHCs",
            "title": "КРАСНАЯ ПОМАДА — душевный ШАНСОН о женской судьбе💔",
            "type": "video",
            "published_at": "2025-10-13T16:01:28Z",
            "duration": "0:03:18",
            "duration_sec": 198,
            "views": 1303,
            "likes": 45,
            "comments": 3,
            "url": "https://www.youtube.com/watch?v=rTa7kvPdHCs"
        },
        {
            "video_id": "Hrn9r92S50w",
            "title": "ЖИЗНЬ КАК ВОДА — Душевная песня о времени",
            "type": "video",
            "published_at": "2025-10-12T10:00:33Z",
            "duration": "0:04:17",
            "duration_sec": 257,
            "views": 14444,
            "likes": 300,
            "comments": 13,
            "url": "https://www.youtube.com/watch?v=Hrn9r92S50w"
        },
        {
            "video_id": "2jvuaFMzQVE",
            "title": "ЖИВИ, ПОКА ЖИВЁТСЯ — Шансон, что тронет душу",
            "type": "video",
            "published_at": "2025-10-11T10:15:00Z",
            "duration": "0:04:40",
            "duration_sec": 280,
            "views": 2360395,
            "likes": 28347,
            "comments": 1193,
            "url": "https://www.youtube.com/watch?v=2jvuaFMzQVE"
        },
        {
            "video_id": "qKKd40K0DGs",
            "title": "ЖИЗНЬ НА ИЗЛОМЕ — ШАНСОН, КОТОРЫЙ ПРОБИРАЕТ ДО СЛЁЗ",
            "type": "video",
            "published_at": "2025-10-10T16:01:36Z",
            "duration": "0:07:14",
            "duration_sec": 434,
            "views": 10987,
            "likes": 236,
            "comments": 9,
            "url": "https://www.youtube.com/watch?v=qKKd40K0DGs"
        },
        {
            "video_id": "xSKIvV4_MkU",
            "title": "ШАНСОН ОБ ЭМИГРАЦИИ — УЕХАЛ В ПАРИЖ, НО ДУША В РОССИИ",
            "type": "video",
            "published_at": "2025-10-09T16:01:49Z",
            "duration": "0:05:12",
            "duration_sec": 312,
            "views": 1948,
            "likes": 56,
            "comments": 5,
            "url": "https://www.youtube.com/watch?v=xSKIvV4_MkU"
        },
        {
            "video_id": "icxIv5EDTTE",
            "title": "Вышел на свободу после 20 лет | ЖИЗНЕННЫЙ ШАНСОН",
            "type": "video",
            "published_at": "2025-10-08T16:01:32Z",
            "duration": "0:03:55",
            "duration_sec": 235,
            "views": 2106,
            "likes": 50,
            "comments": 12,
            "url": "https://www.youtube.com/watch?v=icxIv5EDTTE"
        },
        {
            "video_id": "hxihGHsoBkg",
            "title": "Горькое вино — НОВЫЙ ШАНСОН, который рвёт душу",
            "type": "video",
            "published_at": "2025-10-03T16:01:31Z",
            "duration": "0:05:29",
            "duration_sec": 329,
            "views": 4314,
            "likes": 111,
            "comments": 5,
            "url": "https://www.youtube.com/watch?v=hxihGHsoBkg"
        },
        {
            "video_id": "gFPTUHtkyEU",
            "title": "ЗАКОН ДЖУНГЛЕЙ — песня о жизни и законе улиц",
            "type": "video",
            "published_at": "2025-10-02T16:01:15Z",
            "duration": "0:03:17",
            "duration_sec": 197,
            "views": 909,
            "likes": 24,
            "comments": 4,
            "url": "https://www.youtube.com/watch?v=gFPTUHtkyEU"
        },
        {
            "video_id": "51ex7P70jSI",
            "title": "Вот так гуляли в 90-х… Ностальгический ШАНСОН",
            "type": "video",
            "published_at": "2025-10-01T16:00:10Z",
            "duration": "0:03:55",
            "duration_sec": 235,
            "views": 4653,
            "likes": 97,
            "comments": 10,
            "url": "https://www.youtube.com/watch?v=51ex7P70jSI"
        },
        {
            "video_id": "m2JWfUiL8Ms",
            "title": "ЖИЗНЬ ПРОШЛА, А В КАРМАНЕ ПУСТО — ШАНСОН",
            "type": "video",
            "published_at": "2025-09-30T16:01:24Z",
            "duration": "0:03:50",
            "duration_sec": 230,
            "views": 9670,
            "likes": 178,
            "comments": 10,
            "url": "https://www.youtube.com/watch?v=m2JWfUiL8Ms"
        },
        {
            "video_id": "mMoypO8I9_I",
            "title": "Он встретил её в аэропорту… ШАНСОН, ОТ КОТОРОГО МУРАШКИ",
            "type": "video",
            "published_at": "2025-09-29T16:01:18Z",
            "duration": "0:04:05",
            "duration_sec": 245,
            "views": 1260,
            "likes": 38,
            "comments": 2,
            "url": "https://www.youtube.com/watch?v=mMoypO8I9_I"
        },
        {
            "video_id": "WCJpLBPgB8c",
            "title": "Вернулся домой — никого не осталось… ЖИЗНЕННЫЙ ШАНСОН",
            "type": "video",
            "published_at": "2025-09-28T10:15:02Z",
            "duration": "0:04:05",
            "duration_sec": 245,
            "views": 5223,
            "likes": 128,
            "comments": 5,
            "url": "https://www.youtube.com/watch?v=WCJpLBPgB8c"
        },
        {
            "video_id": "aEimgzgj7Jk",
            "title": "ПЕСНЯ ДЛЯ ТЕХ, КТО ДЕРЖИТСЯ, НЕСМОТРЯ НИ НА ЧТО",
            "type": "video",
            "published_at": "2025-09-27T10:15:00Z",
            "duration": "0:04:44",
            "duration_sec": 284,
            "views": 13196,
            "likes": 336,
            "comments": 14,
            "url": "https://www.youtube.com/watch?v=aEimgzgj7Jk"
        },
        {
            "video_id": "e3Ro8PlltBI",
            "title": "БУКЕТ, ЧТО МЕНЯЕТ СУДЬБУ! Свадебная песня №1",
            "type": "video",
            "published_at": "2025-09-26T16:01:27Z",
            "duration": "0:03:48",
            "duration_sec": 228,
            "views": 487,
            "likes": 20,
            "comments": 2,
            "url": "https://www.youtube.com/watch?v=e3Ro8PlltBI"
        },
        {
            "video_id": "EjQwgH8LItk",
            "title": "СИЛЬНЫЙ ШАНСОН: Мужчина сгорел до пепла",
            "type": "video",
            "published_at": "2025-09-25T16:00:24Z",
            "duration": "0:04:36",
            "duration_sec": 276,
            "views": 2601,
            "likes": 58,
            "comments": 3,
            "url": "https://www.youtube.com/watch?v=EjQwgH8LItk"
        },
        {
            "video_id": "GsLnVy_WIjs",
            "title": "ШАНСОН, ЧТО БЕРЁТ ЗА ДУШУ — «Счастья нет...»",
            "type": "video",
            "published_at": "2025-09-24T16:00:26Z",
            "duration": "0:04:01",
            "duration_sec": 241,
            "views": 2940,
            "likes": 64,
            "comments": 2,
            "url": "https://www.youtube.com/watch?v=GsLnVy_WIjs"
        },
        {
            "video_id": "FTIqYQgGMyA",
            "title": "ГДЕ ГАРМОШКА ПЛАЧЕТ… Душевный застольный ШАНСОН",
            "type": "video",
            "published_at": "2025-09-23T16:00:23Z",
            "duration": "0:04:18",
            "duration_sec": 258,
            "views": 2007,
            "likes": 55,
            "comments": 1,
            "url": "https://www.youtube.com/watch?v=FTIqYQgGMyA"
        },
        {
            "video_id": "jr-CXMGQ42Q",
            "title": "Дорога без конца — ЖИЗНЕННЫЙ ШАНСОН про любовь",
            "type": "video",
            "published_at": "2025-09-22T16:01:15Z",
            "duration": "0:04:05",
            "duration_sec": 245,
            "views": 3195,
            "likes": 77,
            "comments": 5,
            "url": "https://www.youtube.com/watch?v=jr-CXMGQ42Q"
        },
        {
            "video_id": "BqkvIM8Fv-4",
            "title": "Она в золоте — Он в долгах | НОВЫЙ ЖИЗНЕННЫЙ ШАНСОН",
            "type": "video",
            "published_at": "2025-09-21T10:15:01Z",
            "duration": "0:03:16",
            "duration_sec": 196,
            "views": 2023,
            "likes": 36,
            "comments": 3,
            "url": "https://www.youtube.com/watch?v=BqkvIM8Fv-4"
        },
        {
            "video_id": "G46qQ5TZaRE",
            "title": "ЛУЧШАЯ ПЕСНЯ ДЛЯ СВАДЬБЫ! Шансон до слёз",
            "type": "video",
            "published_at": "2025-09-20T10:00:22Z",
            "duration": "0:03:29",
            "duration_sec": 209,
            "views": 1567,
            "likes": 30,
            "comments": 3,
            "url": "https://www.youtube.com/watch?v=G46qQ5TZaRE"
        },
        {
            "video_id": "u8UaVpNBxVQ",
            "title": "Проиграл жизнь в КАРТЫ… | ЖИЗНЕННЫЙ ШАНСОН",
            "type": "video",
            "published_at": "2025-09-19T16:01:47Z",
            "duration": "0:05:19",
            "duration_sec": 319,
            "views": 3009,
            "likes": 50,
            "comments": 1,
            "url": "https://www.youtube.com/watch?v=u8UaVpNBxVQ"
        },
        {
            "video_id": "lQkezERNVAo",
            "title": "Ты помнишь, БРАТ… ШАНСОН О 90-х ДО СЛЁЗ",
            "type": "video",
            "published_at": "2025-09-18T16:01:24Z",
            "duration": "0:04:29",
            "duration_sec": 269,
            "views": 1876,
            "likes": 51,
            "comments": 4,
            "url": "https://www.youtube.com/watch?v=lQkezERNVAo"
        },
        {
            "video_id": "Qt7vHhtRIAY",
            "title": "РЕЛЬСЫ СУДЬБЫ — Новый ШАНСОН, который цепляет!",
            "type": "video",
            "published_at": "2025-09-17T16:00:50Z",
            "duration": "0:03:59",
            "duration_sec": 239,
            "views": 3124,
            "likes": 73,
            "comments": 3,
            "url": "https://www.youtube.com/watch?v=Qt7vHhtRIAY"
        },
        {
            "video_id": "o5g2wCYjSC4",
            "title": "ЗОЛОТО и ПЕПЕЛ — ПРАВДИВЫЙ ШАНСОН О ЖИЗНИ",
            "type": "video",
            "published_at": "2025-09-16T16:01:34Z",
            "duration": "0:03:41",
            "duration_sec": 221,
            "views": 3108,
            "likes": 84,
            "comments": 4,
            "url": "https://www.youtube.com/watch?v=o5g2wCYjSC4"
        },
        {
            "video_id": "vx-dawALCBc",
            "title": "СТАКАН КАК ПРОВОДНИК — Новый ШАНСОН, что рвёт душу",
            "type": "video",
            "published_at": "2025-09-15T16:01:47Z",
            "duration": "0:06:10",
            "duration_sec": 370,
            "views": 30146,
            "likes": 472,
            "comments": 28,
            "url": "https://www.youtube.com/watch?v=vx-dawALCBc"
        },
        {
            "video_id": "DQu_GmjTUxw",
            "title": "ШАНСОН О СВОБОДЕ: «Счастье не в деньгах»",
            "type": "video",
            "published_at": "2025-09-14T10:15:03Z",
            "duration": "0:04:09",
            "duration_sec": 249,
            "views": 5632,
            "likes": 155,
            "comments": 5,
            "url": "https://www.youtube.com/watch?v=DQu_GmjTUxw"
        },
        {
            "video_id": "z5WtoAxfeKg",
            "title": "ДУШЕВНЫЙ ШАНСОН 🎂 ЛУЧШАЯ ПЕСНЯ НА ДЕНЬ РОЖДЕНИЯ",
            "type": "video",
            "published_at": "2025-09-13T10:45:08Z",
            "duration": "0:04:29",
            "duration_sec": 269,
            "views": 45885,
            "likes": 791,
            "comments": 17,
            "url": "https://www.youtube.com/watch?v=z5WtoAxfeKg"
        },
        {
            "video_id": "XK65J05obKU",
            "title": "Песня на разрыв! Новый ШАНСОН о любви и боли",
            "type": "video",
            "published_at": "2025-09-12T16:00:58Z",
            "duration": "0:04:04",
            "duration_sec": 244,
            "views": 2907,
            "likes": 54,
            "comments": 8,
            "url": "https://www.youtube.com/watch?v=XK65J05obKU"
        },
        {
            "video_id": "Dj7Ym8-ubxI",
            "title": "СУДЬБЫ ПОВОРОТЫ | Новый русский шансон",
            "type": "video",
            "published_at": "2025-09-11T16:00:24Z",
            "duration": "0:04:16",
            "duration_sec": 256,
            "views": 2578,
            "likes": 71,
            "comments": 4,
            "url": "https://www.youtube.com/watch?v=Dj7Ym8-ubxI"
        },
        {
            "video_id": "zQiVXXxBGmQ",
            "title": "Русский ШАНСОН до слёз | Жизнь как осень 🍂",
            "type": "video",
            "published_at": "2025-09-10T16:01:49Z",
            "duration": "0:03:25",
            "duration_sec": 205,
            "views": 260546,
            "likes": 4715,
            "comments": 232,
            "url": "https://www.youtube.com/watch?v=zQiVXXxBGmQ"
        },
        {
            "video_id": "8ukpa00aqZA",
            "title": "ЗАСТОЛЬНАЯ ПЕСНЯ для души — «Эх, моя любовь»",
            "type": "video",
            "published_at": "2025-09-09T16:00:28Z",
            "duration": "0:03:18",
            "duration_sec": 198,
            "views": 1342,
            "likes": 30,
            "comments": 2,
            "url": "https://www.youtube.com/watch?v=8ukpa00aqZA"
        },
        {
            "video_id": "mLr9Op4RP1M",
            "title": "ЖИЗНЬ В ИПОТЕКУ — ШАНСОН на разрыв души",
            "type": "video",
            "published_at": "2025-09-08T16:01:19Z",
            "duration": "0:04:39",
            "duration_sec": 279,
            "views": 6539,
            "likes": 149,
            "comments": 14,
            "url": "https://www.youtube.com/watch?v=mLr9Op4RP1M"
        },
        {
            "video_id": "vXw9zJAKBXY",
            "title": "Душевный ШАНСОН о дальнобойщиках 90-х",
            "type": "video",
            "published_at": "2025-09-07T10:45:05Z",
            "duration": "0:03:42",
            "duration_sec": 222,
            "views": 2689,
            "likes": 63,
            "comments": 3,
            "url": "https://www.youtube.com/watch?v=vXw9zJAKBXY"
        },
        {
            "video_id": "xkNMHymhw-c",
            "title": "ШАНСОН на разрыв души — «Дорога в ад»",
            "type": "video",
            "published_at": "2025-09-06T10:15:15Z",
            "duration": "0:04:19",
            "duration_sec": 259,
            "views": 11589,
            "likes": 205,
            "comments": 19,
            "url": "https://www.youtube.com/watch?v=xkNMHymhw-c"
        },
        {
            "video_id": "caOA9C6yMDc",
            "title": "ЭХ, НАЛИВКА! НАСТОЙКА! 🎶 Весёлый застольный шансон",
            "type": "video",
            "published_at": "2025-09-05T16:01:12Z",
            "duration": "0:03:12",
            "duration_sec": 192,
            "views": 1166,
            "likes": 15,
            "comments": 1,
            "url": "https://www.youtube.com/watch?v=caOA9C6yMDc"
        },
        {
            "video_id": "kWqdoYtQ678",
            "title": "Разговор с таксистом | ШАНСОН, что рвёт душу",
            "type": "video",
            "published_at": "2025-09-04T16:01:21Z",
            "duration": "0:04:28",
            "duration_sec": 268,
            "views": 14304,
            "likes": 235,
            "comments": 4,
            "url": "https://www.youtube.com/watch?v=kWqdoYtQ678"
        },
        {
            "video_id": "LofC1LTBM1g",
            "title": "ШАНСОН до слёз | Эти дворы, которых больше нет",
            "type": "video",
            "published_at": "2025-09-03T16:00:43Z",
            "duration": "0:03:38",
            "duration_sec": 218,
            "views": 5464,
            "likes": 137,
            "comments": 10,
            "url": "https://www.youtube.com/watch?v=LofC1LTBM1g"
        },
        {
            "video_id": "BZ4WSeWDEVg",
            "title": "ТАНЦЫ СКВОЗЬ БОЛЬ 💔 ШАНСОН для сильных мужчин",
            "type": "video",
            "published_at": "2025-09-02T16:00:28Z",
            "duration": "0:03:40",
            "duration_sec": 220,
            "views": 3652,
            "likes": 74,
            "comments": 6,
            "url": "https://www.youtube.com/watch?v=BZ4WSeWDEVg"
        },
        {
            "video_id": "Dm-J3AnEnJM",
            "title": "ЭХ, ГУЛЯЙ НАРОД! ЗАСТОЛЬНАЯ ПЕСНЯ для души",
            "type": "video",
            "published_at": "2025-09-01T16:00:20Z",
            "duration": "0:03:25",
            "duration_sec": 205,
            "views": 2461,
            "likes": 58,
            "comments": 2,
            "url": "https://www.youtube.com/watch?v=Dm-J3AnEnJM"
        },
        {
            "video_id": "jM-BRu1vtys",
            "title": "\"1 СЕНТЯБРЯ… ВСЯ ЖИЗНЬ ВПЕРЕДИ\" — песня, что тронет душу",
            "type": "video",
            "published_at": "2025-08-30T22:15:02Z",
            "duration": "0:03:09",
            "duration_sec": 189,
            "views": 20233,
            "likes": 421,
            "comments": 25,
            "url": "https://www.youtube.com/watch?v=jM-BRu1vtys"
        },
        {
            "video_id": "vY04PG_M2RI",
            "title": "ПЕРВОЕ СЕНТЯБРЯ — ШАНСОН, который вернёт тебя в юность",
            "type": "video",
            "published_at": "2025-08-30T10:01:27Z",
            "duration": "0:03:44",
            "duration_sec": 224,
            "views": 12129,
            "likes": 328,
            "comments": 8,
            "url": "https://www.youtube.com/watch?v=vY04PG_M2RI"
        },
        {
            "video_id": "PdRUH-_4Wjg",
            "title": "«Счастье не в деньгах» — ЖИЗНЕННЫЙ ШАНСОН ДО СЛЁЗ",
            "type": "video",
            "published_at": "2025-08-29T16:00:45Z",
            "duration": "0:04:04",
            "duration_sec": 244,
            "views": 119451,
            "likes": 1744,
            "comments": 58,
            "url": "https://www.youtube.com/watch?v=PdRUH-_4Wjg"
        },
        {
            "video_id": "ubDwMf78jGI",
            "title": "Русские Девчонки — ЗАСТОЛЬНАЯ ПЕСНЯ ГОДА 🎶",
            "type": "video",
            "published_at": "2025-08-28T16:01:39Z",
            "duration": "0:03:03",
            "duration_sec": 183,
            "views": 3085,
            "likes": 62,
            "comments": 1,
            "url": "https://www.youtube.com/watch?v=ubDwMf78jGI"
        },
        {
            "video_id": "-85o04DJTvs",
            "title": "ШАНСОН о ДАЛЬНОБОЙЩИКЕ, который пробирает до слёз",
            "type": "video",
            "published_at": "2025-08-27T16:00:00Z",
            "duration": "0:04:01",
            "duration_sec": 241,
            "views": 6282,
            "likes": 109,
            "comments": 5,
            "url": "https://www.youtube.com/watch?v=-85o04DJTvs"
        },
        {
            "video_id": "dPd2bO8CgrY",
            "title": "Эх, дороги судьбы… Душевный русский ШАНСОН",
            "type": "video",
            "published_at": "2025-08-26T16:01:05Z",
            "duration": "0:03:57",
            "duration_sec": 237,
            "views": 6787,
            "likes": 142,
            "comments": 3,
            "url": "https://www.youtube.com/watch?v=dPd2bO8CgrY"
        },
        {
            "video_id": "xB50ZyfRvpw",
            "title": "ШАНСОН о Питере: «Та Самая» с кандибобером из мема",
            "type": "video",
            "published_at": "2025-08-25T16:01:34Z",
            "duration": "0:05:17",
            "duration_sec": 317,
            "views": 1298,
            "likes": 20,
            "comments": 8,
            "url": "https://www.youtube.com/watch?v=xB50ZyfRvpw"
        },
        {
            "video_id": "FBxXhOsOU28",
            "title": "Философский ШАНСОН о жизни и расплате — «Возвратится»",
            "type": "video",
            "published_at": "2025-08-24T11:00:32Z",
            "duration": "0:03:58",
            "duration_sec": 238,
            "views": 27256,
            "likes": 478,
            "comments": 23,
            "url": "https://www.youtube.com/watch?v=FBxXhOsOU28"
        },
        {
            "video_id": "0-cnUZ7nVIQ",
            "title": "Берёза — душа России | Новый русский ШАНСОН",
            "type": "video",
            "published_at": "2025-08-23T11:00:01Z",
            "duration": "0:04:46",
            "duration_sec": 286,
            "views": 2150,
            "likes": 58,
            "comments": 6,
            "url": "https://www.youtube.com/watch?v=0-cnUZ7nVIQ"
        },
        {
            "video_id": "d1HGQbIbiJo",
            "title": "ЗАСТОЛЬНАЯ ПЕСНЯ: Тёща и Свекровь — кто круче?",
            "type": "video",
            "published_at": "2025-08-22T16:01:08Z",
            "duration": "0:03:25",
            "duration_sec": 205,
            "views": 1091,
            "likes": 24,
            "comments": 0,
            "url": "https://www.youtube.com/watch?v=d1HGQbIbiJo"
        },
        {
            "video_id": "1eGNpujR2LY",
            "title": "МОСКВА РЕШАЕТ! Самая мощная песня о столице",
            "type": "video",
            "published_at": "2025-08-21T16:00:04Z",
            "duration": "0:03:52",
            "duration_sec": 232,
            "views": 1356,
            "likes": 23,
            "comments": 1,
            "url": "https://www.youtube.com/watch?v=1eGNpujR2LY"
        },
        {
            "video_id": "KkiDstzPBzc",
            "title": "РЕСТОРАН, ЧТО ИЗМЕНИЛ МОЮ ЖИЗНЬ | ШАНСОН",
            "type": "video",
            "published_at": "2025-08-20T16:00:36Z",
            "duration": "0:04:18",
            "duration_sec": 258,
            "views": 2185,
            "likes": 36,
            "comments": 5,
            "url": "https://www.youtube.com/watch?v=KkiDstzPBzc"
        },
        {
            "video_id": "EJjB3XZwwjs",
            "title": "Мощный ШАНСОН в самое сердце — «Один в зале»",
            "type": "video",
            "published_at": "2025-08-19T16:00:20Z",
            "duration": "0:04:28",
            "duration_sec": 268,
            "views": 72765,
            "likes": 1089,
            "comments": 68,
            "url": "https://www.youtube.com/watch?v=EJjB3XZwwjs"
        },
        {
            "video_id": "urGPwKHZUTk",
            "title": "ЛЕТО в ГЕЛЕНДЖИКЕ — душевный ШАНСОН о первой любви",
            "type": "video",
            "published_at": "2025-08-18T16:01:24Z",
            "duration": "0:03:58",
            "duration_sec": 238,
            "views": 1127,
            "likes": 20,
            "comments": 0,
            "url": "https://www.youtube.com/watch?v=urGPwKHZUTk"
        },
        {
            "video_id": "D2HoPCjL6hg",
            "title": "ЗАСТОЛЬНАЯ ПЕСНЯ — Русская водка и костёр дружбы",
            "type": "video",
            "published_at": "2025-08-17T11:00:30Z",
            "duration": "0:03:06",
            "duration_sec": 186,
            "views": 1180,
            "likes": 24,
            "comments": 1,
            "url": "https://www.youtube.com/watch?v=D2HoPCjL6hg"
        },
        {
            "video_id": "IDjEjKvJS0g",
            "title": "История Машуни: любовь и плен. ШАНСОН на разрыв",
            "type": "video",
            "published_at": "2025-08-16T10:00:33Z",
            "duration": "0:07:47",
            "duration_sec": 467,
            "views": 581,
            "likes": 21,
            "comments": 1,
            "url": "https://www.youtube.com/watch?v=IDjEjKvJS0g"
        },
        {
            "video_id": "dUv7qbWX-TE",
            "title": "ШАНСОН: Охранник и запретная любовь Мисс Москва-91",
            "type": "video",
            "published_at": "2025-08-15T16:01:08Z",
            "duration": "0:03:25",
            "duration_sec": 205,
            "views": 1194,
            "likes": 18,
            "comments": 0,
            "url": "https://www.youtube.com/watch?v=dUv7qbWX-TE"
        },
        {
            "video_id": "TD4Igf8b0IY",
            "title": "ЖИЗНЬ КАК РЮМКА — ШАНСОН ПРО КАЖДОГО ИЗ НАС",
            "type": "video",
            "published_at": "2025-08-14T16:00:49Z",
            "duration": "0:04:53",
            "duration_sec": 293,
            "views": 358908,
            "likes": 4245,
            "comments": 172,
            "url": "https://www.youtube.com/watch?v=TD4Igf8b0IY"
        },
        {
            "video_id": "VHZpETnr7s8",
            "title": "ШАНСОН НА БРАЙТОН-БИЧ — ПЕСНЯ, ЧТО ВЕРНЁТ ТЕБЯ ДОМОЙ",
            "type": "video",
            "published_at": "2025-08-13T16:01:01Z",
            "duration": "0:05:47",
            "duration_sec": 347,
            "views": 2364,
            "likes": 35,
            "comments": 7,
            "url": "https://www.youtube.com/watch?v=VHZpETnr7s8"
        },
        {
            "video_id": "oq2TpLhIcUc",
            "title": "ШАНСОН на День Рождения – душевно до слёз",
            "type": "video",
            "published_at": "2025-08-12T16:01:26Z",
            "duration": "0:04:07",
            "duration_sec": 247,
            "views": 382394,
            "likes": 5414,
            "comments": 122,
            "url": "https://www.youtube.com/watch?v=oq2TpLhIcUc"
        },
        {
            "video_id": "FONibM--OHQ",
            "title": "ШАНСОН О РЫНКЕ, КОТОРОГО БОЛЬШЕ НЕТ",
            "type": "video",
            "published_at": "2025-08-11T16:00:26Z",
            "duration": "0:05:23",
            "duration_sec": 323,
            "views": 1157,
            "likes": 17,
            "comments": 2,
            "url": "https://www.youtube.com/watch?v=FONibM--OHQ"
        },
        {
            "video_id": "Nd7SCDmzzJE",
            "title": "ОНА ВЫБРАЛА ГИТАРИСТА… А Я — МОСКВА-РЕКУ | ШАНСОН",
            "type": "video",
            "published_at": "2025-08-10T16:00:46Z",
            "duration": "0:02:53",
            "duration_sec": 173,
            "views": 1367,
            "likes": 18,
            "comments": 1,
            "url": "https://www.youtube.com/watch?v=Nd7SCDmzzJE"
        },
        {
            "video_id": "wj5kjlIOm6g",
            "title": "Я БЫЛ ГЛАВОЙ БАНДЫ... А теперь пою ШАНСОН до слёз",
            "type": "video",
            "published_at": "2025-08-09T10:01:35Z",
            "duration": "0:03:26",
            "duration_sec": 206,
            "views": 3143,
            "likes": 61,
            "comments": 7,
            "url": "https://www.youtube.com/watch?v=wj5kjlIOm6g"
        },
        {
            "video_id": "3K1B0phK4A0",
            "title": "ОНА ПОСМОТРЕЛА — И Я ПРОПАЛ | НОВЫЙ ШАНСОН 2025",
            "type": "video",
            "published_at": "2025-08-08T16:00:06Z",
            "duration": "0:03:10",
            "duration_sec": 190,
            "views": 1289,
            "likes": 31,
            "comments": 4,
            "url": "https://www.youtube.com/watch?v=3K1B0phK4A0"
        },
        {
            "video_id": "38E06WSxL60",
            "title": "Скучаю по 90-м. ШАНСОН до мурашек",
            "type": "video",
            "published_at": "2025-08-07T16:00:10Z",
            "duration": "0:05:10",
            "duration_sec": 310,
            "views": 3048,
            "likes": 57,
            "comments": 4,
            "url": "https://www.youtube.com/watch?v=38E06WSxL60"
        },
        {
            "video_id": "QQTXpHI5RjU",
            "title": "ШАНСОН до слёз — ОТЕЦ поёт о СЫНЕ-герое",
            "type": "video",
            "published_at": "2025-08-06T16:00:45Z",
            "duration": "0:03:00",
            "duration_sec": 180,
            "views": 1504,
            "likes": 27,
            "comments": 4,
            "url": "https://www.youtube.com/watch?v=QQTXpHI5RjU"
        },
        {
            "video_id": "IZLy8FiwAoA",
            "title": "ПРЕДАЛ РОДИТЕЛЕЙ — а мать всё ждала... ШАНСОН",
            "type": "video",
            "published_at": "2025-08-05T16:00:26Z",
            "duration": "0:03:10",
            "duration_sec": 190,
            "views": 3112,
            "likes": 54,
            "comments": 4,
            "url": "https://www.youtube.com/watch?v=IZLy8FiwAoA"
        },
        {
            "video_id": "Es4oBVn66FQ",
            "title": "ШАНСОН НА СВАДЬБЕ — отец спел для дочери-невесты",
            "type": "video",
            "published_at": "2025-08-04T16:00:22Z",
            "duration": "0:03:29",
            "duration_sec": 209,
            "views": 1151,
            "likes": 23,
            "comments": 3,
            "url": "https://www.youtube.com/watch?v=Es4oBVn66FQ"
        },
        {
            "video_id": "oVgI-fRtQMg",
            "title": "Главный ШАНСОН для настоящего ЗАСТОЛЬЯ!",
            "type": "video",
            "published_at": "2025-08-03T16:01:17Z",
            "duration": "0:04:59",
            "duration_sec": 299,
            "views": 1325,
            "likes": 42,
            "comments": 0,
            "url": "https://www.youtube.com/watch?v=oVgI-fRtQMg"
        },
        {
            "video_id": "WJp1RSKKG5k",
            "title": "Она ушла к богатому — а он стал звездой | Реальный Шансон",
            "type": "video",
            "published_at": "2025-08-02T10:00:46Z",
            "duration": "0:04:22",
            "duration_sec": 262,
            "views": 2255,
            "likes": 45,
            "comments": 7,
            "url": "https://www.youtube.com/watch?v=WJp1RSKKG5k"
        },
        {
            "video_id": "wCPeE0inwow",
            "title": "ПЕСНЯ-ШАНСОН про Наташу, которую мы ВСЕ знаем",
            "type": "video",
            "published_at": "2025-08-01T16:01:42Z",
            "duration": "0:03:10",
            "duration_sec": 190,
            "views": 2158,
            "likes": 54,
            "comments": 4,
            "url": "https://www.youtube.com/watch?v=wCPeE0inwow"
        },
        {
            "video_id": "33Yv-ZSax4I",
            "title": "ЛЮБИЛ АЛЛУ ПУГАЧЁВУ ЗА РЕШЁТКОЙ — ШАНСОН ДО СЛЁЗ",
            "type": "video",
            "published_at": "2025-07-31T16:00:05Z",
            "duration": "0:02:50",
            "duration_sec": 170,
            "views": 1578,
            "likes": 20,
            "comments": 2,
            "url": "https://www.youtube.com/watch?v=33Yv-ZSax4I"
        },
        {
            "video_id": "CvmEq4v75AM",
            "title": "МОСКВА 90-Х: ШАНСОН, ОТ КОТОРОГО МУРАШКИ ПО КОЖЕ",
            "type": "video",
            "published_at": "2025-07-30T16:00:24Z",
            "duration": "0:03:26",
            "duration_sec": 206,
            "views": 1754,
            "likes": 31,
            "comments": 2,
            "url": "https://www.youtube.com/watch?v=CvmEq4v75AM"
        },
        {
            "video_id": "ETjzUGYygIQ",
            "title": "Жил — копил… А жить забыл | Сильный ШАНСОН о жизни",
            "type": "video",
            "published_at": "2025-07-29T16:00:31Z",
            "duration": "0:02:57",
            "duration_sec": 177,
            "views": 865567,
            "likes": 10986,
            "comments": 483,
            "url": "https://www.youtube.com/watch?v=ETjzUGYygIQ"
        },
        {
            "video_id": "4ghoHElmL7o",
            "title": "ШАНСОН о ТРЁХ официантках, в которых влюблён Таганрог",
            "type": "video",
            "published_at": "2025-07-28T16:00:08Z",
            "duration": "0:03:36",
            "duration_sec": 216,
            "views": 2528,
            "likes": 31,
            "comments": 0,
            "url": "https://www.youtube.com/watch?v=4ghoHElmL7o"
        },
        {
            "video_id": "xvinlc5Fk8o",
            "title": "УЕХАЛ — НО НЕ ЗАБЫЛ | ГРУСТНЫЙ ШАНСОН ОБ ЭМИГРАЦИИ",
            "type": "video",
            "published_at": "2025-07-27T16:01:31Z",
            "duration": "0:02:58",
            "duration_sec": 178,
            "views": 1940,
            "likes": 40,
            "comments": 5,
            "url": "https://www.youtube.com/watch?v=xvinlc5Fk8o"
        },
        {
            "video_id": "BTSiWaIkO0A",
            "title": "СЛЁЗЫ на глазах… ШАНСОН про сестёр из детдома",
            "type": "video",
            "published_at": "2025-07-26T10:00:30Z",
            "duration": "0:03:15",
            "duration_sec": 195,
            "views": 927,
            "likes": 16,
            "comments": 1,
            "url": "https://www.youtube.com/watch?v=BTSiWaIkO0A"
        },
        {
            "video_id": "lIlxyGlOdnk",
            "title": "ШАНСОН ко Дню ВМФ — Слушают все моряки!",
            "type": "video",
            "published_at": "2025-07-25T10:01:31Z",
            "duration": "0:03:10",
            "duration_sec": 190,
            "views": 6355,
            "likes": 109,
            "comments": 17,
            "url": "https://www.youtube.com/watch?v=lIlxyGlOdnk"
        },
        {
            "video_id": "QITUbN8SxSQ",
            "title": "ГОРЯЧИЙ ШАНСОН ИЗ БАНИ 🔥 ЖИЗНЬ БЕЗ ФИЛЬТРА",
            "type": "video",
            "published_at": "2025-07-24T16:00:46Z",
            "duration": "0:02:34",
            "duration_sec": 154,
            "views": 1854,
            "likes": 29,
            "comments": 2,
            "url": "https://www.youtube.com/watch?v=QITUbN8SxSQ"
        },
        {
            "video_id": "rZErDlyoEPg",
            "title": "ШАНСОН о КАЗИНО, который пробирает до мурашек",
            "type": "video",
            "published_at": "2025-07-23T16:01:37Z",
            "duration": "0:05:38",
            "duration_sec": 338,
            "views": 987,
            "likes": 21,
            "comments": 6,
            "url": "https://www.youtube.com/watch?v=rZErDlyoEPg"
        },
        {
            "video_id": "dgZjhBqiMxA",
            "title": "Он увидел МАРИНУ — и написал ШАНСОН всей жизни",
            "type": "video",
            "published_at": "2025-07-22T16:01:08Z",
            "duration": "0:03:20",
            "duration_sec": 200,
            "views": 8418,
            "likes": 109,
            "comments": 11,
            "url": "https://www.youtube.com/watch?v=dgZjhBqiMxA"
        },
        {
            "video_id": "mmN_CDgYS3E",
            "title": "Шансон, который должен услышать каждый… МАМА, ПРОСТИ ЗА ВСЁ",
            "type": "video",
            "published_at": "2025-07-21T16:01:22Z",
            "duration": "0:02:14",
            "duration_sec": 134,
            "views": 3861,
            "likes": 83,
            "comments": 6,
            "url": "https://www.youtube.com/watch?v=mmN_CDgYS3E"
        },
        {
            "video_id": "1rPPp-u7KFg",
            "title": "ОНА БЫЛА КОРОЛЕВОЙ... ШАНСОН О ЖЕНСКОЙ СУДЬБЕ",
            "type": "video",
            "published_at": "2025-07-20T16:00:02Z",
            "duration": "0:02:29",
            "duration_sec": 149,
            "views": 917,
            "likes": 10,
            "comments": 1,
            "url": "https://www.youtube.com/watch?v=1rPPp-u7KFg"
        },
        {
            "video_id": "z5Lj-73d-yc",
            "title": "ЗАСТОЛЬНАЯ ПЕСНЯ, КОТОРУЮ ИЩУТ ВСЕ! 🎉 ШАНСОН ОТ ДУШИ",
            "type": "video",
            "published_at": "2025-07-19T10:01:30Z",
            "duration": "0:03:15",
            "duration_sec": 195,
            "views": 34865,
            "likes": 475,
            "comments": 15,
            "url": "https://www.youtube.com/watch?v=z5Lj-73d-yc"
        },
        {
            "video_id": "mf9NAeHkSiw",
            "title": "Он мечтал об отце… а нашёл алкаша | ЖЕСТКИЙ ШАНСОН",
            "type": "video",
            "published_at": "2025-07-18T10:01:37Z",
            "duration": "0:03:17",
            "duration_sec": 197,
            "views": 1103,
            "likes": 14,
            "comments": 3,
            "url": "https://www.youtube.com/watch?v=mf9NAeHkSiw"
        },
        {
            "video_id": "MT-S0wdgDvQ",
            "title": "Ростов и Одесса ЗАПЕЛИ! ШАНСОН от души!",
            "type": "video",
            "published_at": "2025-07-17T16:00:43Z",
            "duration": "0:03:07",
            "duration_sec": 187,
            "views": 7180,
            "likes": 120,
            "comments": 9,
            "url": "https://www.youtube.com/watch?v=MT-S0wdgDvQ"
        },
        {
            "video_id": "3VnyCqVJs2M",
            "title": "ЛЮБОВНИК УШЁЛ К ДОЧЕРИ?! ЖЕНСКИЙ ШАНСОН О ПРЕДАТЕЛЬСТВЕ",
            "type": "video",
            "published_at": "2025-07-16T16:00:05Z",
            "duration": "0:03:11",
            "duration_sec": 191,
            "views": 508,
            "likes": 12,
            "comments": 1,
            "url": "https://www.youtube.com/watch?v=3VnyCqVJs2M"
        },
        {
            "video_id": "FeGUsRGO8uc",
            "title": "С ДНЁМ РОЖДЕНИЯ! ЛУЧШИЙ ШАНСОН ДЛЯ ПРАЗДНИКА",
            "type": "video",
            "published_at": "2025-07-15T16:00:22Z",
            "duration": "0:03:19",
            "duration_sec": 199,
            "views": 154120,
            "likes": 1659,
            "comments": 39,
            "url": "https://www.youtube.com/watch?v=FeGUsRGO8uc"
        },
        {
            "video_id": "WXOvjE7Hqqk",
            "title": "ЖЕНА УШЛА, ДРУЗЬЯ МОЛЧАТ — НОВЫЙ ШАНСОН ДО СЛЁЗ",
            "type": "video",
            "published_at": "2025-07-14T16:00:54Z",
            "duration": "0:03:26",
            "duration_sec": 206,
            "views": 12615,
            "likes": 188,
            "comments": 8,
            "url": "https://www.youtube.com/watch?v=WXOvjE7Hqqk"
        },
        {
            "video_id": "Uli5cqeILtU",
            "title": "СВАДЬБА НА 500 ГОСТЕЙ — ШАНСОН, КОТОРЫЙ ТРОНУЛ ВСЕХ!",
            "type": "video",
            "published_at": "2025-07-13T10:00:44Z",
            "duration": "0:04:45",
            "duration_sec": 285,
            "views": 12813,
            "likes": 154,
            "comments": 15,
            "url": "https://www.youtube.com/watch?v=Uli5cqeILtU"
        },
        {
            "video_id": "ScrWfExPbN0",
            "title": "ШАНСОН ко Дню Рыбака — Каждому мужику в душу!",
            "type": "video",
            "published_at": "2025-07-12T10:00:45Z",
            "duration": "0:03:10",
            "duration_sec": 190,
            "views": 4812,
            "likes": 69,
            "comments": 4,
            "url": "https://www.youtube.com/watch?v=ScrWfExPbN0"
        },
        {
            "video_id": "Ks-Pba0quVU",
            "title": "СЛУШАЙ ЭТУ ПЕСНЮ КАЖДЫЙ ДЕНЬ — СТАНЕШЬ БОГАТЫМ!",
            "type": "video",
            "published_at": "2025-07-11T16:00:40Z",
            "duration": "0:03:05",
            "duration_sec": 185,
            "views": 1048,
            "likes": 18,
            "comments": 0,
            "url": "https://www.youtube.com/watch?v=Ks-Pba0quVU"
        },
        {
            "video_id": "OcVuU-7XKa0",
            "title": "РОСТОВСКИЙ ШАНСОН из Испании — до дна за батю! 🥃",
            "type": "video",
            "published_at": "2025-07-10T16:00:50Z",
            "duration": "0:03:09",
            "duration_sec": 189,
            "views": 1135,
            "likes": 17,
            "comments": 3,
            "url": "https://www.youtube.com/watch?v=OcVuU-7XKa0"
        },
        {
            "video_id": "Hp8aRhzhApI",
            "title": "КРАСНОДАР ЛУЧШЕ ЛОС-АНДЖЕЛЕСА?! 🔥 СЛУШАЙ СРОЧНО!",
            "type": "video",
            "published_at": "2025-07-08T16:00:28Z",
            "duration": "0:03:42",
            "duration_sec": 222,
            "views": 1093,
            "likes": 23,
            "comments": 5,
            "url": "https://www.youtube.com/watch?v=Hp8aRhzhApI"
        },
        {
            "video_id": "9OSq4SPTAgs",
            "title": "ШАНСОН до слёз — Он уехал, а пацаны остались там...",
            "type": "video",
            "published_at": "2025-07-06T10:00:12Z",
            "duration": "0:02:54",
            "duration_sec": 174,
            "views": 2175,
            "likes": 24,
            "comments": 1,
            "url": "https://www.youtube.com/watch?v=9OSq4SPTAgs"
        },
        {
            "video_id": "32hyR0NrawA",
            "title": "ШАНСОН О РОСТОВЕ, КОТОРЫЙ ПРОБИВАЕТ ДО СЛЁЗ",
            "type": "video",
            "published_at": "2025-07-05T18:15:01Z",
            "duration": "0:03:19",
            "duration_sec": 199,
            "views": 15680,
            "likes": 175,
            "comments": 13,
            "url": "https://www.youtube.com/watch?v=32hyR0NrawA"
        },
        {
            "video_id": "esYlmZ-8wVY",
            "title": "Он жил между Москвой и Питером… ШАНСОН до слёз",
            "type": "video",
            "published_at": "2025-07-04T16:01:14Z",
            "duration": "0:03:21",
            "duration_sec": 201,
            "views": 2248,
            "likes": 32,
            "comments": 1,
            "url": "https://www.youtube.com/watch?v=esYlmZ-8wVY"
        },
        {
            "video_id": "rvRVJsJRWyM",
            "title": "\"Люба, любовь\" — НОВЫЙ ШАНСОН, что тронет сердце",
            "type": "video",
            "published_at": "2025-07-03T16:15:10Z",
            "duration": "0:04:26",
            "duration_sec": 266,
            "views": 1048,
            "likes": 25,
            "comments": 0,
            "url": "https://www.youtube.com/watch?v=rvRVJsJRWyM"
        },
        {
            "video_id": "FFYOu6m9KjA",
            "title": "Застольная песня, как тост — за всех, кто за столом! До мурашек…",
            "type": "video",
            "published_at": "2025-07-02T16:00:23Z",
            "duration": "0:02:59",
            "duration_sec": 179,
            "views": 12196,
            "likes": 187,
            "comments": 4,
            "url": "https://www.youtube.com/watch?v=FFYOu6m9KjA"
        }
    ]
}